sleap_anipose/__init__.py
sleap_anipose/calibration.py
sleap_anipose/triangulation.py
sleap_anipose-0.1.8.dist-info/LICENSE
sleap_anipose-0.1.8.dist-info/METADATA
sleap_anipose-0.1.8.dist-info/WHEEL
sleap_anipose-0.1.8.dist-info/entry_points.txt
sleap_anipose-0.1.8.dist-info/top_level.txt
sleap_anipose-0.1.8.dist-info/RECORD
