Metadata-Version: 2.1
Name: sleap-anipose
Version: 0.1.8
Summary: SLEAP to Anipose triangulation pipeline for 3D multi-animal pose tracking.
Home-page: https://github.com/talmolab/sleap-anipose
Author: Sean Afshar
Author-email: safshar@salk.edu
Maintainer: Talmo Pereira
Maintainer-email: talmo@salk.edu
License: BSD 3-Clause License
Keywords: sleap,pose tracking,pose estimation,behavior
Classifier: Programming Language :: Python :: 3
License-File: LICENSE
Requires-Dist: matplotlib
Requires-Dist: h5py
Requires-Dist: imageio
Requires-Dist: imageio-ffmpeg
Requires-Dist: opencv-contrib-python <4.7.0
Requires-Dist: aniposelib
Requires-Dist: click
Provides-Extra: dev
Requires-Dist: pytest ; extra == 'dev'
Requires-Dist: pytest-cov ; extra == 'dev'
Requires-Dist: black ; extra == 'dev'
Requires-Dist: pydocstyle ; extra == 'dev'
Requires-Dist: toml ; extra == 'dev'
Requires-Dist: twine ; extra == 'dev'
Requires-Dist: build ; extra == 'dev'
